{
"x": 8,
"y": -14,
"biomeType": "PLAINS",
"tileData": [
	[ 1, 10, 10, 1, 10, 1, 10, 10, 1, 1, 1, 1, 1, 1, 1, 1 ],
	[ 10, 1, 23, 10, 10, 1, 1, 1, 1, 23, 10, 1, 1, 24, 24, 10 ],
	[ 1, 24, 10, 1, 1, 24, 1, 10, 10, 1, 10, 1, 10, 10, 1, 1 ],
	[ 10, 24, 10, 1, 10, 1, 1, 10, 24, 1, 1, 10, 10, 1, 1, 10 ],
	[ 1, 1, 1, 1, 10, 1, 23, 10, 1, 10, 1, 24, 1, 24, 10, 1 ],
	[ 1, 1, 10, 10, 1, 1, 1, 1, 1, 1, 1, 1, 1, 24, 1, 1 ],
	[ 1, 24, 1, 1, 1, 24, 10, 10, 1, 1, 1, 1, 1, 1, 1, 10 ],
	[ 1, 1, 1, 1, 1, 1, 1, 1, 1, 1, 24, 10, 10, 1, 1, 10 ],
	[ 1, 10, 1, 24, 10, 1, 1, 24, 10, 10, 1, 10, 1, 10, 1, 10 ],
	[ 1, 1, 10, 1, 1, 1, 1, 1, 10, 1, 10, 1, 24, 10, 1, 24 ],
	[ 1, 1, 10, 1, 10, 10, 10, 10, 10, 1, 1, 24, 1, 24, 10, 1 ],
	[ 1, 10, 1, 10, 10, 10, 1, 10, 10, 1, 10, 1, 10, 1, 1, 1 ],
	[ 10, 1, 1, 1, 24, 24, 1, 1, 1, 1, 1, 10, 24, 10, 1, 1 ],
	[ 1, 1, 24, 1, 1, 10, 10, 1, 1, 1, 10, 10, 10, 1, 10, 1 ],
	[ 1, 10, 1, 24, 10, 1, 1, 1, 1, 1, 10, 1, 10, 1, 10, 10 ],
	[ 1, 1, 24, 24, 1, 1, 1, 1, 1, 10, 1, 1, 1, 10, 10, 1 ]
],
"objects": [
	{
		"class": "io.github.pokemeetup.system.gameplay.overworld.World$WorldObjectData",
		"x": 4576,
		"y": -6976,
		"type": "TREE_0"
	},
	{
		"class": "io.github.pokemeetup.system.gameplay.overworld.World$WorldObjectData",
		"x": 4224,
		"y": -7008,
		"type": "TREE_0"
	},
	{
		"class": "io.github.pokemeetup.system.gameplay.overworld.World$WorldObjectData",
		"x": 4352,
		"y": -6944,
		"type": "TREE_0"
	},
	{
		"class": "io.github.pokemeetup.system.gameplay.overworld.World$WorldObjectData",
		"x": 4352,
		"y": -6784,
		"type": "TREE_0"
	},
	{
		"class": "io.github.pokemeetup.system.gameplay.overworld.World$WorldObjectData",
		"x": 4352,
		"y": -7136,
		"type": "TREE_0"
	},
	{
		"class": "io.github.pokemeetup.system.gameplay.overworld.World$WorldObjectData",
		"x": 4384,
		"y": -7040,
		"type": "TREE_0"
	},
	{
		"class": "io.github.pokemeetup.system.gameplay.overworld.World$WorldObjectData",
		"x": 4512,
		"y": -6688,
		"type": "TREE_0"
	},
	{
		"class": "io.github.pokemeetup.system.gameplay.overworld.World$WorldObjectData",
		"x": 4512,
		"y": -6848,
		"type": "TREE_0"
	},
	{
		"class": "io.github.pokemeetup.system.gameplay.overworld.World$WorldObjectData",
		"x": 4224,
		"y": -6688,
		"type": "TREE_0"
	},
	{
		"class": "io.github.pokemeetup.system.gameplay.overworld.World$WorldObjectData",
		"x": 4576,
		"y": -7168,
		"type": "TREE_0"
	},
	{
		"class": "io.github.pokemeetup.system.gameplay.overworld.World$WorldObjectData",
		"x": 4128,
		"y": -6816,
		"type": "TREE_0"
	},
	{
		"class": "io.github.pokemeetup.system.gameplay.overworld.World$WorldObjectData",
		"x": 4128,
		"y": -6944,
		"type": "TREE_0"
	},
	{
		"class": "io.github.pokemeetup.system.gameplay.overworld.World$WorldObjectData",
		"x": 4256,
		"y": -7136,
		"type": "TREE_1"
	},
	{
		"class": "io.github.pokemeetup.system.gameplay.overworld.World$WorldObjectData",
		"x": 4160,
		"y": -7136,
		"type": "TREE_1"
	},
	{
		"class": "io.github.pokemeetup.system.gameplay.overworld.World$WorldObjectData",
		"x": 4224,
		"y": -6816,
		"type": "TREE_1"
	},
	{
		"class": "io.github.pokemeetup.system.gameplay.overworld.World$WorldObjectData",
		"x": 4512,
		"y": -7072,
		"type": "SUNFLOWER"
	},
	{
		"class": "io.github.pokemeetup.system.gameplay.overworld.World$WorldObjectData",
		"x": 4416,
		"y": -6816,
		"type": "SUNFLOWER"
	},
	{
		"class": "io.github.pokemeetup.system.gameplay.overworld.World$WorldObjectData",
		"x": 4480,
		"y": -6944,
		"type": "SUNFLOWER"
	},
	{
		"class": "io.github.pokemeetup.system.gameplay.overworld.World$WorldObjectData",
		"x": 4320,
		"y": -6688,
		"type": "APRICORN_TREE"
	},
	{
		"class": "io.github.pokemeetup.system.gameplay.overworld.World$WorldObjectData",
		"x": 4128,
		"y": -7008,
		"type": "POKEBALL"
	}
],
"blocks": [],
"lastModified": 0,
"isMultiplayer": false
}