{
"x": -24,
"y": -83,
"biomeType": "RUINS",
"tileData": [
	[ 56, 56, 53, 55, 56, 56, 56, 55, 54, 55, 54, 56, 56, 56, 54, 56 ],
	[ 56, 56, 56, 54, 56, 56, 54, 56, 55, 56, 56, 56, 56, 56, 56, 56 ],
	[ 56, 56, 54, 56, 56, 56, 56, 56, 53, 56, 56, 56, 53, 56, 55, 56 ],
	[ 53, 56, 53, 56, 56, 56, 56, 56, 56, 56, 56, 54, 55, 56, 56, 56 ],
	[ 55, 56, 56, 53, 56, 53, 56, 54, 56, 56, 56, 54, 56, 56, 56, 56 ],
	[ 56, 56, 54, 56, 56, 56, 55, 54, 56, 56, 55, 56, 56, 55, 56, 56 ],
	[ 56, 54, 56, 54, 56, 56, 56, 56, 56, 56, 56, 56, 56, 54, 56, 56 ],
	[ 56, 56, 56, 54, 53, 56, 56, 54, 55, 56, 56, 56, 56, 56, 56, 56 ],
	[ 54, 55, 55, 55, 55, 56, 53, 56, 54, 56, 53, 53, 56, 56, 1, 56 ],
	[ 56, 55, 55, 56, 56, 55, 56, 56, 56, 56, 56, 56, 56, 24, 1, 10 ],
	[ 53, 56, 56, 56, 54, 55, 56, 56, 56, 56, 56, 56, 1, 10, 1, 1 ],
	[ 56, 56, 56, 56, 56, 55, 56, 53, 56, 56, 56, 54, 1, 56, 10, 10 ],
	[ 56, 56, 56, 53, 54, 56, 56, 54, 56, 56, 54, 1, 24, 10, 1, 1 ],
	[ 56, 56, 56, 56, 56, 55, 56, 56, 54, 56, 56, 1, 24, 54, 1, 1 ],
	[ 56, 56, 53, 56, 56, 56, 56, 54, 1, 10, 56, 10, 56, 1, 24, 1 ],
	[ 1, 56, 56, 54, 54, 56, 54, 10, 54, 10, 54, 1, 1, 10, 10, 1 ]
],
"objects": [
	{
		"class": "io.github.pokemeetup.system.gameplay.overworld.World$WorldObjectData",
		"x": -11808,
		"y": -42304,
		"type": "RUINS_TREE"
	},
	{
		"class": "io.github.pokemeetup.system.gameplay.overworld.World$WorldObjectData",
		"x": -12160,
		"y": -42336,
		"type": "RUINS_TREE"
	},
	{
		"class": "io.github.pokemeetup.system.gameplay.overworld.World$WorldObjectData",
		"x": -12032,
		"y": -42272,
		"type": "RUINS_TREE"
	},
	{
		"class": "io.github.pokemeetup.system.gameplay.overworld.World$WorldObjectData",
		"x": -12032,
		"y": -42112,
		"type": "RUINS_TREE"
	},
	{
		"class": "io.github.pokemeetup.system.gameplay.overworld.World$WorldObjectData",
		"x": -12032,
		"y": -42464,
		"type": "RUINS_TREE"
	},
	{
		"class": "io.github.pokemeetup.system.gameplay.overworld.World$WorldObjectData",
		"x": -12000,
		"y": -42368,
		"type": "RUINS_TREE"
	},
	{
		"class": "io.github.pokemeetup.system.gameplay.overworld.World$WorldObjectData",
		"x": -11872,
		"y": -42176,
		"type": "RUINS_TREE"
	},
	{
		"class": "io.github.pokemeetup.system.gameplay.overworld.World$WorldObjectData",
		"x": -12160,
		"y": -42016,
		"type": "RUINS_TREE"
	},
	{
		"class": "io.github.pokemeetup.system.gameplay.overworld.World$WorldObjectData",
		"x": -12256,
		"y": -42144,
		"type": "RUINS_TREE"
	},
	{
		"class": "io.github.pokemeetup.system.gameplay.overworld.World$WorldObjectData",
		"x": -12256,
		"y": -42272,
		"type": "RUINS_TREE"
	},
	{
		"class": "io.github.pokemeetup.system.gameplay.overworld.World$WorldObjectData",
		"x": -12128,
		"y": -42464,
		"type": "RUINS_TREE"
	},
	{
		"class": "io.github.pokemeetup.system.gameplay.overworld.World$WorldObjectData",
		"x": -11936,
		"y": -42080,
		"type": "RUINS_TREE"
	},
	{
		"class": "io.github.pokemeetup.system.gameplay.overworld.World$WorldObjectData",
		"x": -12224,
		"y": -42464,
		"type": "RUINS_TREE"
	},
	{
		"class": "io.github.pokemeetup.system.gameplay.overworld.World$WorldObjectData",
		"x": -12160,
		"y": -42144,
		"type": "RUINS_TREE"
	},
	{
		"class": "io.github.pokemeetup.system.gameplay.overworld.World$WorldObjectData",
		"x": -11808,
		"y": -42464,
		"type": "RUINS_TREE"
	},
	{
		"class": "io.github.pokemeetup.system.gameplay.overworld.World$WorldObjectData",
		"x": -11904,
		"y": -42272,
		"type": "RUINS_TREE"
	},
	{
		"class": "io.github.pokemeetup.system.gameplay.overworld.World$WorldObjectData",
		"x": -11904,
		"y": -42432,
		"type": "RUINS_TREE"
	},
	{
		"class": "io.github.pokemeetup.system.gameplay.overworld.World$WorldObjectData",
		"x": -12064,
		"y": -42016,
		"type": "RUINS_TREE"
	},
	{
		"class": "io.github.pokemeetup.system.gameplay.overworld.World$WorldObjectData",
		"x": -12128,
		"y": -42240,
		"type": "RUINS_TREE"
	},
	{
		"class": "io.github.pokemeetup.system.gameplay.overworld.World$WorldObjectData",
		"x": -12288,
		"y": -42368,
		"type": "RUINS_TREE"
	},
	{
		"class": "io.github.pokemeetup.system.gameplay.overworld.World$WorldObjectData",
		"x": -11808,
		"y": -42144,
		"type": "POKEBALL"
	}
],
"blocks": [],
"lastModified": 0,
"isMultiplayer": false
}