{
"x": -19,
"y": -86,
"biomeType": "PLAINS",
"tileData": [
	[ 1, 1, 10, 1, 24, 1, 24, 1, 1, 1, 10, 1, 10, 1, 1, 1 ],
	[ 10, 10, 24, 1, 10, 1, 10, 1, 10, 10, 1, 1, 1, 10, 1, 10 ],
	[ 10, 1, 23, 1, 1, 24, 1, 10, 1, 10, 1, 1, 24, 1, 1, 10 ],
	[ 1, 1, 10, 24, 10, 10, 1, 24, 1, 10, 10, 24, 10, 1, 10, 10 ],
	[ 1, 10, 10, 1, 1, 1, 10, 10, 1, 1, 24, 1, 1, 10, 24, 1 ],
	[ 1, 10, 10, 1, 1, 1, 10, 1, 10, 1, 1, 1, 10, 10, 1, 10 ],
	[ 1, 10, 1, 1, 24, 1, 10, 10, 10, 1, 10, 24, 23, 10, 24, 1 ],
	[ 1, 1, 1, 10, 23, 24, 1, 24, 1, 10, 1, 10, 1, 1, 1, 1 ],
	[ 1, 1, 1, 10, 1, 1, 10, 10, 1, 10, 10, 10, 24, 24, 1, 10 ],
	[ 1, 10, 10, 1, 1, 10, 10, 1, 1, 10, 10, 1, 10, 1, 1, 1 ],
	[ 24, 10, 23, 1, 1, 10, 1, 10, 1, 10, 1, 10, 10, 1, 1, 10 ],
	[ 10, 10, 24, 10, 1, 1, 1, 10, 10, 24, 1, 1, 1, 24, 24, 10 ],
	[ 1, 1, 1, 1, 10, 24, 10, 1, 1, 10, 1, 1, 10, 10, 1, 24 ],
	[ 1, 24, 1, 1, 1, 10, 1, 1, 10, 10, 1, 1, 1, 1, 10, 24 ],
	[ 1, 1, 10, 10, 24, 1, 24, 10, 1, 10, 1, 24, 1, 1, 10, 1 ],
	[ 1, 10, 10, 1, 1, 10, 24, 1, 1, 1, 9, 5, 7, 10, 5, 7 ]
],
"objects": [
	{
		"class": "io.github.pokemeetup.system.gameplay.overworld.World$WorldObjectData",
		"x": -9248,
		"y": -43840,
		"type": "TREE_0"
	},
	{
		"class": "io.github.pokemeetup.system.gameplay.overworld.World$WorldObjectData",
		"x": -9600,
		"y": -43872,
		"type": "TREE_0"
	},
	{
		"class": "io.github.pokemeetup.system.gameplay.overworld.World$WorldObjectData",
		"x": -9472,
		"y": -43808,
		"type": "TREE_0"
	},
	{
		"class": "io.github.pokemeetup.system.gameplay.overworld.World$WorldObjectData",
		"x": -9472,
		"y": -43648,
		"type": "TREE_0"
	},
	{
		"class": "io.github.pokemeetup.system.gameplay.overworld.World$WorldObjectData",
		"x": -9472,
		"y": -44000,
		"type": "TREE_0"
	},
	{
		"class": "io.github.pokemeetup.system.gameplay.overworld.World$WorldObjectData",
		"x": -9440,
		"y": -43904,
		"type": "TREE_0"
	},
	{
		"class": "io.github.pokemeetup.system.gameplay.overworld.World$WorldObjectData",
		"x": -9312,
		"y": -43552,
		"type": "TREE_0"
	},
	{
		"class": "io.github.pokemeetup.system.gameplay.overworld.World$WorldObjectData",
		"x": -9312,
		"y": -43712,
		"type": "TREE_0"
	},
	{
		"class": "io.github.pokemeetup.system.gameplay.overworld.World$WorldObjectData",
		"x": -9600,
		"y": -43552,
		"type": "TREE_0"
	},
	{
		"class": "io.github.pokemeetup.system.gameplay.overworld.World$WorldObjectData",
		"x": -9248,
		"y": -44032,
		"type": "TREE_0"
	},
	{
		"class": "io.github.pokemeetup.system.gameplay.overworld.World$WorldObjectData",
		"x": -9696,
		"y": -43680,
		"type": "TREE_0"
	},
	{
		"class": "io.github.pokemeetup.system.gameplay.overworld.World$WorldObjectData",
		"x": -9696,
		"y": -43808,
		"type": "TREE_0"
	},
	{
		"class": "io.github.pokemeetup.system.gameplay.overworld.World$WorldObjectData",
		"x": -9568,
		"y": -44000,
		"type": "TREE_1"
	},
	{
		"class": "io.github.pokemeetup.system.gameplay.overworld.World$WorldObjectData",
		"x": -9664,
		"y": -44000,
		"type": "TREE_1"
	},
	{
		"class": "io.github.pokemeetup.system.gameplay.overworld.World$WorldObjectData",
		"x": -9600,
		"y": -43680,
		"type": "TREE_1"
	},
	{
		"class": "io.github.pokemeetup.system.gameplay.overworld.World$WorldObjectData",
		"x": -9312,
		"y": -43936,
		"type": "SUNFLOWER"
	},
	{
		"class": "io.github.pokemeetup.system.gameplay.overworld.World$WorldObjectData",
		"x": -9408,
		"y": -43680,
		"type": "SUNFLOWER"
	},
	{
		"class": "io.github.pokemeetup.system.gameplay.overworld.World$WorldObjectData",
		"x": -9344,
		"y": -43808,
		"type": "SUNFLOWER"
	},
	{
		"class": "io.github.pokemeetup.system.gameplay.overworld.World$WorldObjectData",
		"x": -9504,
		"y": -43552,
		"type": "APRICORN_TREE"
	},
	{
		"class": "io.github.pokemeetup.system.gameplay.overworld.World$WorldObjectData",
		"x": -9504,
		"y": -43712,
		"type": "POKEBALL"
	}
],
"blocks": [],
"lastModified": 0,
"isMultiplayer": false
}