{
"x": 4,
"y": -15,
"biomeType": "PLAINS",
"tileData": [
	[ 1, 1, 1, 10, 10, 1, 1, 10, 1, 1, 1, 24, 1, 10, 1, 1 ],
	[ 1, 10, 1, 10, 1, 10, 24, 10, 1, 1, 24, 22, 10, 10, 1, 1 ],
	[ 1, 10, 24, 1, 10, 10, 1, 10, 1, 24, 1, 24, 1, 1, 1, 10 ],
	[ 10, 1, 10, 1, 10, 10, 1, 1, 10, 1, 1, 24, 10, 1, 10, 10 ],
	[ 1, 24, 10, 1, 10, 10, 1, 10, 10, 10, 10, 10, 1, 1, 1, 10 ],
	[ 10, 10, 1, 10, 1, 1, 10, 10, 1, 10, 1, 1, 1, 10, 10, 1 ],
	[ 10, 24, 10, 1, 1, 10, 10, 10, 10, 1, 10, 1, 1, 1, 1, 1 ],
	[ 1, 1, 1, 1, 1, 1, 10, 1, 10, 1, 1, 22, 1, 24, 22, 1 ],
	[ 10, 10, 10, 1, 1, 23, 10, 1, 1, 10, 1, 10, 10, 1, 10, 1 ],
	[ 1, 1, 24, 10, 24, 1, 1, 1, 1, 10, 1, 1, 10, 1, 1, 10 ],
	[ 10, 1, 1, 10, 10, 10, 1, 1, 24, 24, 1, 1, 10, 1, 1, 10 ],
	[ 10, 10, 1, 10, 1, 1, 1, 24, 10, 1, 24, 1, 1, 1, 1, 1 ],
	[ 1, 10, 1, 1, 1, 1, 1, 1, 10, 24, 1, 10, 24, 1, 24, 1 ],
	[ 24, 24, 10, 1, 10, 22, 10, 1, 1, 1, 1, 1, 22, 1, 24, 1 ],
	[ 10, 1, 1, 10, 24, 1, 10, 1, 10, 1, 1, 24, 1, 24, 22, 10 ],
	[ 1, 1, 1, 22, 1, 10, 24, 10, 10, 1, 10, 10, 10, 10, 1, 1 ]
],
"objects": [
	{
		"class": "io.github.pokemeetup.system.gameplay.overworld.World$WorldObjectData",
		"x": 2528,
		"y": -7488,
		"type": "TREE_0"
	},
	{
		"class": "io.github.pokemeetup.system.gameplay.overworld.World$WorldObjectData",
		"x": 2176,
		"y": -7520,
		"type": "TREE_0"
	},
	{
		"class": "io.github.pokemeetup.system.gameplay.overworld.World$WorldObjectData",
		"x": 2304,
		"y": -7456,
		"type": "TREE_0"
	},
	{
		"class": "io.github.pokemeetup.system.gameplay.overworld.World$WorldObjectData",
		"x": 2304,
		"y": -7296,
		"type": "TREE_0"
	},
	{
		"class": "io.github.pokemeetup.system.gameplay.overworld.World$WorldObjectData",
		"x": 2304,
		"y": -7648,
		"type": "TREE_0"
	},
	{
		"class": "io.github.pokemeetup.system.gameplay.overworld.World$WorldObjectData",
		"x": 2336,
		"y": -7552,
		"type": "TREE_0"
	},
	{
		"class": "io.github.pokemeetup.system.gameplay.overworld.World$WorldObjectData",
		"x": 2464,
		"y": -7200,
		"type": "TREE_0"
	},
	{
		"class": "io.github.pokemeetup.system.gameplay.overworld.World$WorldObjectData",
		"x": 2464,
		"y": -7360,
		"type": "TREE_0"
	},
	{
		"class": "io.github.pokemeetup.system.gameplay.overworld.World$WorldObjectData",
		"x": 2176,
		"y": -7200,
		"type": "TREE_0"
	},
	{
		"class": "io.github.pokemeetup.system.gameplay.overworld.World$WorldObjectData",
		"x": 2528,
		"y": -7680,
		"type": "TREE_0"
	},
	{
		"class": "io.github.pokemeetup.system.gameplay.overworld.World$WorldObjectData",
		"x": 2080,
		"y": -7328,
		"type": "TREE_0"
	},
	{
		"class": "io.github.pokemeetup.system.gameplay.overworld.World$WorldObjectData",
		"x": 2080,
		"y": -7456,
		"type": "TREE_0"
	},
	{
		"class": "io.github.pokemeetup.system.gameplay.overworld.World$WorldObjectData",
		"x": 2208,
		"y": -7648,
		"type": "TREE_1"
	},
	{
		"class": "io.github.pokemeetup.system.gameplay.overworld.World$WorldObjectData",
		"x": 2112,
		"y": -7648,
		"type": "TREE_1"
	},
	{
		"class": "io.github.pokemeetup.system.gameplay.overworld.World$WorldObjectData",
		"x": 2176,
		"y": -7328,
		"type": "TREE_1"
	},
	{
		"class": "io.github.pokemeetup.system.gameplay.overworld.World$WorldObjectData",
		"x": 2464,
		"y": -7584,
		"type": "SUNFLOWER"
	},
	{
		"class": "io.github.pokemeetup.system.gameplay.overworld.World$WorldObjectData",
		"x": 2368,
		"y": -7328,
		"type": "SUNFLOWER"
	},
	{
		"class": "io.github.pokemeetup.system.gameplay.overworld.World$WorldObjectData",
		"x": 2432,
		"y": -7456,
		"type": "SUNFLOWER"
	},
	{
		"class": "io.github.pokemeetup.system.gameplay.overworld.World$WorldObjectData",
		"x": 2272,
		"y": -7200,
		"type": "APRICORN_TREE"
	},
	{
		"class": "io.github.pokemeetup.system.gameplay.overworld.World$WorldObjectData",
		"x": 2272,
		"y": -7584,
		"type": "POKEBALL"
	}
],
"blocks": [],
"lastModified": 0,
"isMultiplayer": false
}