{
"x": -168,
"y": -4,
"biomeType": "PLAINS",
"tileData": [
	[ 1, 10, 10, 1, 1, 1, 10, 10, 10, 1, 22, 1, 1, 1, 1, 1 ],
	[ 1, 1, 1, 1, 1, 1, 10, 1, 10, 10, 24, 1, 1, 10, 10, 1 ],
	[ 1, 10, 1, 22, 10, 1, 1, 1, 24, 1, 10, 10, 1, 1, 1, 1 ],
	[ 10, 24, 1, 1, 10, 1, 1, 24, 24, 1, 1, 1, 10, 1, 10, 1 ],
	[ 10, 1, 1, 1, 1, 1, 24, 23, 1, 24, 1, 1, 1, 10, 10, 1 ],
	[ 1, 1, 1, 1, 1, 1, 10, 10, 1, 1, 1, 1, 24, 10, 10, 10 ],
	[ 10, 1, 1, 10, 10, 1, 10, 23, 1, 1, 10, 10, 23, 1, 10, 1 ],
	[ 10, 1, 1, 10, 1, 24, 1, 1, 10, 1, 10, 10, 1, 10, 10, 10 ],
	[ 10, 10, 10, 10, 24, 10, 1, 1, 1, 10, 24, 1, 1, 10, 10, 1 ],
	[ 1, 10, 1, 1, 1, 1, 10, 1, 10, 1, 24, 24, 10, 1, 10, 10 ],
	[ 1, 1, 10, 1, 10, 1, 1, 1, 1, 10, 24, 1, 1, 10, 10, 1 ],
	[ 10, 1, 24, 1, 1, 10, 1, 10, 1, 24, 1, 1, 10, 10, 1, 1 ],
	[ 10, 24, 10, 10, 1, 10, 10, 23, 1, 10, 1, 1, 1, 1, 24, 10 ],
	[ 1, 10, 1, 10, 24, 24, 10, 1, 1, 10, 10, 22, 10, 1, 10, 1 ],
	[ 10, 10, 10, 1, 1, 1, 1, 10, 1, 10, 10, 1, 1, 1, 10, 10 ],
	[ 1, 1, 24, 1, 10, 10, 10, 10, 10, 24, 1, 10, 24, 1, 10, 1 ]
],
"objects": [
	{
		"class": "io.github.pokemeetup.system.gameplay.overworld.World$WorldObjectData",
		"x": -85920,
		"y": -1728,
		"type": "TREE_0"
	},
	{
		"class": "io.github.pokemeetup.system.gameplay.overworld.World$WorldObjectData",
		"x": -85920,
		"y": -2016,
		"type": "TREE_0"
	},
	{
		"class": "io.github.pokemeetup.system.gameplay.overworld.World$WorldObjectData",
		"x": -85696,
		"y": -1600,
		"type": "TREE_0"
	},
	{
		"class": "io.github.pokemeetup.system.gameplay.overworld.World$WorldObjectData",
		"x": -85984,
		"y": -1856,
		"type": "TREE_0"
	},
	{
		"class": "io.github.pokemeetup.system.gameplay.overworld.World$WorldObjectData",
		"x": -85792,
		"y": -1760,
		"type": "TREE_0"
	},
	{
		"class": "io.github.pokemeetup.system.gameplay.overworld.World$WorldObjectData",
		"x": -85728,
		"y": -1952,
		"type": "TREE_0"
	},
	{
		"class": "io.github.pokemeetup.system.gameplay.overworld.World$WorldObjectData",
		"x": -86016,
		"y": -1728,
		"type": "TREE_0"
	},
	{
		"class": "io.github.pokemeetup.system.gameplay.overworld.World$WorldObjectData",
		"x": -85600,
		"y": -1728,
		"type": "TREE_0"
	},
	{
		"class": "io.github.pokemeetup.system.gameplay.overworld.World$WorldObjectData",
		"x": -85600,
		"y": -1952,
		"type": "TREE_0"
	},
	{
		"class": "io.github.pokemeetup.system.gameplay.overworld.World$WorldObjectData",
		"x": -85824,
		"y": -1888,
		"type": "TREE_0"
	},
	{
		"class": "io.github.pokemeetup.system.gameplay.overworld.World$WorldObjectData",
		"x": -85600,
		"y": -1856,
		"type": "TREE_0"
	},
	{
		"class": "io.github.pokemeetup.system.gameplay.overworld.World$WorldObjectData",
		"x": -85536,
		"y": -1568,
		"type": "TREE_0"
	},
	{
		"class": "io.github.pokemeetup.system.gameplay.overworld.World$WorldObjectData",
		"x": -85728,
		"y": -1856,
		"type": "TREE_0"
	},
	{
		"class": "io.github.pokemeetup.system.gameplay.overworld.World$WorldObjectData",
		"x": -85888,
		"y": -1600,
		"type": "TREE_0"
	},
	{
		"class": "io.github.pokemeetup.system.gameplay.overworld.World$WorldObjectData",
		"x": -85824,
		"y": -2016,
		"type": "TREE_1"
	},
	{
		"class": "io.github.pokemeetup.system.gameplay.overworld.World$WorldObjectData",
		"x": -85728,
		"y": -1760,
		"type": "SUNFLOWER"
	},
	{
		"class": "io.github.pokemeetup.system.gameplay.overworld.World$WorldObjectData",
		"x": -85632,
		"y": -2048,
		"type": "SUNFLOWER"
	},
	{
		"class": "io.github.pokemeetup.system.gameplay.overworld.World$WorldObjectData",
		"x": -85632,
		"y": -1568,
		"type": "SUNFLOWER"
	},
	{
		"class": "io.github.pokemeetup.system.gameplay.overworld.World$WorldObjectData",
		"x": -85920,
		"y": -1856,
		"type": "SUNFLOWER"
	},
	{
		"class": "io.github.pokemeetup.system.gameplay.overworld.World$WorldObjectData",
		"x": -85536,
		"y": -1856,
		"type": "SUNFLOWER"
	},
	{
		"class": "io.github.pokemeetup.system.gameplay.overworld.World$WorldObjectData",
		"x": -85952,
		"y": -1632,
		"type": "POKEBALL"
	}
],
"blocks": [],
"lastModified": 0,
"isMultiplayer": false
}