{
"x": -149,
"y": -11,
"biomeType": "FOREST",
"tileData": [
	[ 1, 10, 1, 11, 11, 11, 1, 12, 11, 11, 12, 11, 12, 11, 11, 11 ],
	[ 11, 12, 11, 11, 12, 12, 20, 1, 10, 1, 11, 11, 12, 1, 11, 12 ],
	[ 11, 11, 11, 1, 1, 10, 10, 11, 12, 11, 11, 12, 11, 1, 11, 12 ],
	[ 12, 11, 11, 12, 11, 11, 12, 12, 11, 12, 1, 11, 11, 11, 11, 11 ],
	[ 11, 11, 12, 11, 11, 1, 11, 11, 11, 12, 11, 12, 12, 1, 11, 11 ],
	[ 11, 12, 11, 11, 1, 12, 12, 11, 12, 1, 10, 11, 10, 11, 12, 1 ],
	[ 11, 12, 11, 1, 10, 11, 11, 12, 11, 10, 11, 1, 11, 1, 12, 11 ],
	[ 11, 12, 1, 12, 11, 12, 10, 11, 11, 11, 11, 11, 11, 11, 11, 12 ],
	[ 11, 12, 11, 11, 12, 12, 11, 1, 11, 11, 11, 12, 1, 10, 11, 10 ],
	[ 11, 1, 11, 11, 10, 1, 11, 12, 12, 12, 11, 12, 10, 11, 1, 10 ],
	[ 11, 11, 11, 12, 12, 1, 11, 12, 11, 11, 1, 1, 11, 12, 10, 11 ],
	[ 11, 11, 12, 11, 10, 1, 10, 11, 12, 12, 11, 11, 10, 1, 11, 1 ],
	[ 1, 12, 12, 11, 12, 11, 11, 11, 1, 12, 11, 12, 11, 11, 11, 11 ],
	[ 11, 10, 12, 12, 11, 11, 12, 11, 11, 12, 1, 11, 11, 1, 11, 11 ],
	[ 1, 11, 1, 11, 11, 12, 11, 11, 1, 12, 11, 11, 11, 10, 12, 11 ],
	[ 1, 12, 11, 11, 1, 1, 10, 12, 11, 11, 11, 11, 11, 11, 1, 11 ]
],
"objects": [
	{
		"class": "io.github.pokemeetup.system.gameplay.overworld.World$WorldObjectData",
		"x": -76192,
		"y": -5312,
		"type": "TREE_0"
	},
	{
		"class": "io.github.pokemeetup.system.gameplay.overworld.World$WorldObjectData",
		"x": -76192,
		"y": -5600,
		"type": "TREE_0"
	},
	{
		"class": "io.github.pokemeetup.system.gameplay.overworld.World$WorldObjectData",
		"x": -75968,
		"y": -5184,
		"type": "TREE_0"
	},
	{
		"class": "io.github.pokemeetup.system.gameplay.overworld.World$WorldObjectData",
		"x": -76256,
		"y": -5440,
		"type": "TREE_0"
	},
	{
		"class": "io.github.pokemeetup.system.gameplay.overworld.World$WorldObjectData",
		"x": -76064,
		"y": -5344,
		"type": "TREE_0"
	},
	{
		"class": "io.github.pokemeetup.system.gameplay.overworld.World$WorldObjectData",
		"x": -76000,
		"y": -5536,
		"type": "TREE_0"
	},
	{
		"class": "io.github.pokemeetup.system.gameplay.overworld.World$WorldObjectData",
		"x": -76288,
		"y": -5312,
		"type": "TREE_0"
	},
	{
		"class": "io.github.pokemeetup.system.gameplay.overworld.World$WorldObjectData",
		"x": -75872,
		"y": -5312,
		"type": "TREE_0"
	},
	{
		"class": "io.github.pokemeetup.system.gameplay.overworld.World$WorldObjectData",
		"x": -75872,
		"y": -5536,
		"type": "TREE_0"
	},
	{
		"class": "io.github.pokemeetup.system.gameplay.overworld.World$WorldObjectData",
		"x": -76096,
		"y": -5472,
		"type": "TREE_0"
	},
	{
		"class": "io.github.pokemeetup.system.gameplay.overworld.World$WorldObjectData",
		"x": -75872,
		"y": -5440,
		"type": "TREE_0"
	},
	{
		"class": "io.github.pokemeetup.system.gameplay.overworld.World$WorldObjectData",
		"x": -75808,
		"y": -5152,
		"type": "TREE_0"
	},
	{
		"class": "io.github.pokemeetup.system.gameplay.overworld.World$WorldObjectData",
		"x": -76000,
		"y": -5440,
		"type": "TREE_0"
	},
	{
		"class": "io.github.pokemeetup.system.gameplay.overworld.World$WorldObjectData",
		"x": -76160,
		"y": -5184,
		"type": "TREE_0"
	},
	{
		"class": "io.github.pokemeetup.system.gameplay.overworld.World$WorldObjectData",
		"x": -76096,
		"y": -5600,
		"type": "TREE_0"
	},
	{
		"class": "io.github.pokemeetup.system.gameplay.overworld.World$WorldObjectData",
		"x": -75904,
		"y": -5632,
		"type": "TREE_1"
	},
	{
		"class": "io.github.pokemeetup.system.gameplay.overworld.World$WorldObjectData",
		"x": -76288,
		"y": -5600,
		"type": "TREE_1"
	},
	{
		"class": "io.github.pokemeetup.system.gameplay.overworld.World$WorldObjectData",
		"x": -76064,
		"y": -5152,
		"type": "TREE_1"
	},
	{
		"class": "io.github.pokemeetup.system.gameplay.overworld.World$WorldObjectData",
		"x": -76032,
		"y": -5248,
		"type": "POKEBALL"
	}
],
"blocks": [],
"lastModified": 0,
"isMultiplayer": false
}