{
"x": -49,
"y": -2,
"biomeType": "HAUNTED",
"tileData": [
	[ 7, 5, 7, 7, 5, 5, 7, 9, 5, 5, 7, 7, 5, 8, 7, 5 ],
	[ 5, 5, 5, 7, 5, 5, 5, 5, 7, 5, 9, 7, 5, 5, 5, 5 ],
	[ 7, 5, 7, 7, 8, 7, 5, 5, 5, 7, 7, 5, 5, 7, 5, 7 ],
	[ 5, 9, 5, 5, 9, 5, 5, 5, 5, 5, 1, 9, 5, 7, 5, 7 ],
	[ 5, 5, 8, 5, 5, 5, 5, 7, 5, 7, 7, 5, 7, 5, 1, 9 ],
	[ 5, 5, 9, 5, 5, 5, 5, 7, 8, 5, 7, 5, 5, 5, 5, 7 ],
	[ 5, 5, 5, 7, 7, 5, 5, 7, 7, 5, 5, 8, 5, 7, 9, 7 ],
	[ 5, 5, 5, 7, 7, 9, 10, 9, 5, 5, 5, 8, 5, 5, 5, 7 ],
	[ 5, 5, 5, 7, 1, 10, 5, 5, 5, 1, 5, 5, 8, 7, 5, 7 ],
	[ 5, 5, 9, 5, 8, 7, 5, 5, 7, 5, 5, 7, 9, 5, 5, 8 ],
	[ 5, 5, 5, 8, 7, 5, 5, 7, 5, 5, 1, 5, 5, 5, 7, 1 ],
	[ 9, 7, 7, 9, 5, 7, 7, 7, 5, 10, 5, 5, 5, 7, 5, 7 ],
	[ 5, 5, 9, 5, 5, 1, 5, 5, 5, 5, 5, 7, 7, 5, 5, 7 ],
	[ 5, 9, 5, 5, 5, 7, 7, 5, 5, 5, 5, 7, 5, 7, 5, 5 ],
	[ 9, 5, 5, 5, 5, 5, 5, 5, 5, 5, 5, 5, 5, 7, 5, 5 ],
	[ 5, 5, 8, 5, 5, 7, 7, 5, 7, 8, 8, 5, 9, 5, 5, 5 ]
],
"objects": [
	{
		"class": "io.github.pokemeetup.system.gameplay.overworld.World$WorldObjectData",
		"x": -24672,
		"y": -672,
		"type": "HAUNTED_TREE"
	},
	{
		"class": "io.github.pokemeetup.system.gameplay.overworld.World$WorldObjectData",
		"x": -24864,
		"y": -640,
		"type": "HAUNTED_TREE"
	},
	{
		"class": "io.github.pokemeetup.system.gameplay.overworld.World$WorldObjectData",
		"x": -24800,
		"y": -896,
		"type": "HAUNTED_TREE"
	},
	{
		"class": "io.github.pokemeetup.system.gameplay.overworld.World$WorldObjectData",
		"x": -24704,
		"y": -992,
		"type": "HAUNTED_TREE"
	},
	{
		"class": "io.github.pokemeetup.system.gameplay.overworld.World$WorldObjectData",
		"x": -25088,
		"y": -672,
		"type": "HAUNTED_TREE"
	},
	{
		"class": "io.github.pokemeetup.system.gameplay.overworld.World$WorldObjectData",
		"x": -24992,
		"y": -768,
		"type": "HAUNTED_TREE"
	},
	{
		"class": "io.github.pokemeetup.system.gameplay.overworld.World$WorldObjectData",
		"x": -24640,
		"y": -768,
		"type": "HAUNTED_TREE"
	},
	{
		"class": "io.github.pokemeetup.system.gameplay.overworld.World$WorldObjectData",
		"x": -25024,
		"y": -992,
		"type": "HAUNTED_TREE"
	},
	{
		"class": "io.github.pokemeetup.system.gameplay.overworld.World$WorldObjectData",
		"x": -24672,
		"y": -544,
		"type": "HAUNTED_TREE"
	},
	{
		"class": "io.github.pokemeetup.system.gameplay.overworld.World$WorldObjectData",
		"x": -24992,
		"y": -864,
		"type": "HAUNTED_TREE"
	},
	{
		"class": "io.github.pokemeetup.system.gameplay.overworld.World$WorldObjectData",
		"x": -24800,
		"y": -768,
		"type": "HAUNTED_TREE"
	},
	{
		"class": "io.github.pokemeetup.system.gameplay.overworld.World$WorldObjectData",
		"x": -24928,
		"y": -1024,
		"type": "HAUNTED_TREE"
	},
	{
		"class": "io.github.pokemeetup.system.gameplay.overworld.World$WorldObjectData",
		"x": -24896,
		"y": -544,
		"type": "HAUNTED_TREE"
	},
	{
		"class": "io.github.pokemeetup.system.gameplay.overworld.World$WorldObjectData",
		"x": -25088,
		"y": -896,
		"type": "HAUNTED_TREE"
	},
	{
		"class": "io.github.pokemeetup.system.gameplay.overworld.World$WorldObjectData",
		"x": -24832,
		"y": -992,
		"type": "HAUNTED_TREE"
	},
	{
		"class": "io.github.pokemeetup.system.gameplay.overworld.World$WorldObjectData",
		"x": -24896,
		"y": -832,
		"type": "HAUNTED_TREE"
	},
	{
		"class": "io.github.pokemeetup.system.gameplay.overworld.World$WorldObjectData",
		"x": -25088,
		"y": -544,
		"type": "HAUNTED_TREE"
	},
	{
		"class": "io.github.pokemeetup.system.gameplay.overworld.World$WorldObjectData",
		"x": -24704,
		"y": -864,
		"type": "HAUNTED_TREE"
	},
	{
		"class": "io.github.pokemeetup.system.gameplay.overworld.World$WorldObjectData",
		"x": -25088,
		"y": -768,
		"type": "HAUNTED_TREE"
	},
	{
		"class": "io.github.pokemeetup.system.gameplay.overworld.World$WorldObjectData",
		"x": -24960,
		"y": -640,
		"type": "HAUNTED_TREE"
	},
	{
		"class": "io.github.pokemeetup.system.gameplay.overworld.World$WorldObjectData",
		"x": -24608,
		"y": -864,
		"type": "HAUNTED_TREE"
	},
	{
		"class": "io.github.pokemeetup.system.gameplay.overworld.World$WorldObjectData",
		"x": -24768,
		"y": -672,
		"type": "HAUNTED_TREE"
	},
	{
		"class": "io.github.pokemeetup.system.gameplay.overworld.World$WorldObjectData",
		"x": -24992,
		"y": -544,
		"type": "HAUNTED_TREE"
	},
	{
		"class": "io.github.pokemeetup.system.gameplay.overworld.World$WorldObjectData",
		"x": -24768,
		"y": -544,
		"type": "HAUNTED_TREE"
	},
	{
		"class": "io.github.pokemeetup.system.gameplay.overworld.World$WorldObjectData",
		"x": -24736,
		"y": -768,
		"type": "DEAD_TREE"
	},
	{
		"class": "io.github.pokemeetup.system.gameplay.overworld.World$WorldObjectData",
		"x": -24608,
		"y": -576,
		"type": "DEAD_TREE"
	},
	{
		"class": "io.github.pokemeetup.system.gameplay.overworld.World$WorldObjectData",
		"x": -24928,
		"y": -736,
		"type": "DEAD_TREE"
	},
	{
		"class": "io.github.pokemeetup.system.gameplay.overworld.World$WorldObjectData",
		"x": -24608,
		"y": -1024,
		"type": "DEAD_TREE"
	},
	{
		"class": "io.github.pokemeetup.system.gameplay.overworld.World$WorldObjectData",
		"x": -24928,
		"y": -928,
		"type": "DEAD_TREE"
	},
	{
		"class": "io.github.pokemeetup.system.gameplay.overworld.World$WorldObjectData",
		"x": -24992,
		"y": -704,
		"type": "POKEBALL"
	}
],
"blocks": [],
"lastModified": 0,
"isMultiplayer": false
}