{
"x": -18,
"y": -3,
"biomeType": "FOREST",
"tileData": [
	[ 12, 11, 11, 11, 1, 11, 11, 11, 11, 11, 12, 1, 12, 1, 12, 11 ],
	[ 11, 11, 11, 12, 11, 11, 12, 11, 11, 20, 1, 11, 11, 1, 11, 11 ],
	[ 11, 11, 11, 1, 12, 1, 11, 11, 11, 10, 10, 12, 12, 11, 11, 12 ],
	[ 12, 10, 11, 11, 1, 11, 11, 11, 12, 11, 12, 1, 11, 11, 12, 1 ],
	[ 12, 11, 1, 10, 11, 11, 11, 1, 11, 11, 10, 11, 12, 12, 11, 11 ],
	[ 11, 12, 11, 20, 11, 11, 12, 11, 11, 12, 11, 11, 12, 11, 11, 10 ],
	[ 12, 12, 11, 11, 11, 12, 12, 11, 12, 11, 11, 1, 11, 11, 11, 1 ],
	[ 11, 11, 11, 12, 12, 11, 12, 12, 11, 11, 11, 12, 11, 11, 12, 11 ],
	[ 11, 11, 11, 11, 11, 12, 11, 11, 11, 12, 1, 11, 1, 11, 11, 11 ],
	[ 11, 1, 12, 11, 11, 11, 11, 12, 12, 11, 1, 11, 1, 11, 11, 12 ],
	[ 12, 11, 12, 11, 11, 11, 11, 1, 10, 12, 12, 11, 11, 11, 1, 12 ],
	[ 11, 11, 11, 1, 11, 11, 12, 1, 11, 1, 12, 11, 12, 12, 11, 11 ],
	[ 12, 11, 10, 11, 11, 11, 1, 20, 12, 12, 11, 11, 11, 11, 20, 12 ],
	[ 11, 12, 11, 12, 11, 10, 11, 1, 12, 11, 11, 1, 1, 12, 12, 1 ],
	[ 1, 11, 11, 11, 11, 11, 11, 11, 11, 11, 12, 11, 11, 12, 11, 11 ],
	[ 10, 1, 11, 1, 12, 12, 11, 12, 11, 12, 11, 1, 11, 11, 11, 11 ]
],
"objects": [
	{
		"class": "io.github.pokemeetup.system.gameplay.overworld.World$WorldObjectData",
		"x": -8800,
		"y": -1184,
		"type": "TREE_0"
	},
	{
		"class": "io.github.pokemeetup.system.gameplay.overworld.World$WorldObjectData",
		"x": -8992,
		"y": -1152,
		"type": "TREE_0"
	},
	{
		"class": "io.github.pokemeetup.system.gameplay.overworld.World$WorldObjectData",
		"x": -8928,
		"y": -1408,
		"type": "TREE_0"
	},
	{
		"class": "io.github.pokemeetup.system.gameplay.overworld.World$WorldObjectData",
		"x": -8832,
		"y": -1504,
		"type": "TREE_0"
	},
	{
		"class": "io.github.pokemeetup.system.gameplay.overworld.World$WorldObjectData",
		"x": -9216,
		"y": -1184,
		"type": "TREE_0"
	},
	{
		"class": "io.github.pokemeetup.system.gameplay.overworld.World$WorldObjectData",
		"x": -9120,
		"y": -1280,
		"type": "TREE_0"
	},
	{
		"class": "io.github.pokemeetup.system.gameplay.overworld.World$WorldObjectData",
		"x": -8768,
		"y": -1280,
		"type": "TREE_0"
	},
	{
		"class": "io.github.pokemeetup.system.gameplay.overworld.World$WorldObjectData",
		"x": -9152,
		"y": -1504,
		"type": "TREE_0"
	},
	{
		"class": "io.github.pokemeetup.system.gameplay.overworld.World$WorldObjectData",
		"x": -8800,
		"y": -1056,
		"type": "TREE_0"
	},
	{
		"class": "io.github.pokemeetup.system.gameplay.overworld.World$WorldObjectData",
		"x": -9120,
		"y": -1376,
		"type": "TREE_0"
	},
	{
		"class": "io.github.pokemeetup.system.gameplay.overworld.World$WorldObjectData",
		"x": -8928,
		"y": -1280,
		"type": "TREE_0"
	},
	{
		"class": "io.github.pokemeetup.system.gameplay.overworld.World$WorldObjectData",
		"x": -9056,
		"y": -1536,
		"type": "TREE_0"
	},
	{
		"class": "io.github.pokemeetup.system.gameplay.overworld.World$WorldObjectData",
		"x": -9024,
		"y": -1056,
		"type": "TREE_0"
	},
	{
		"class": "io.github.pokemeetup.system.gameplay.overworld.World$WorldObjectData",
		"x": -9216,
		"y": -1408,
		"type": "TREE_0"
	},
	{
		"class": "io.github.pokemeetup.system.gameplay.overworld.World$WorldObjectData",
		"x": -8960,
		"y": -1504,
		"type": "TREE_0"
	},
	{
		"class": "io.github.pokemeetup.system.gameplay.overworld.World$WorldObjectData",
		"x": -9024,
		"y": -1344,
		"type": "TREE_0"
	},
	{
		"class": "io.github.pokemeetup.system.gameplay.overworld.World$WorldObjectData",
		"x": -9216,
		"y": -1056,
		"type": "TREE_0"
	},
	{
		"class": "io.github.pokemeetup.system.gameplay.overworld.World$WorldObjectData",
		"x": -8832,
		"y": -1376,
		"type": "TREE_0"
	},
	{
		"class": "io.github.pokemeetup.system.gameplay.overworld.World$WorldObjectData",
		"x": -9216,
		"y": -1280,
		"type": "TREE_1"
	},
	{
		"class": "io.github.pokemeetup.system.gameplay.overworld.World$WorldObjectData",
		"x": -9088,
		"y": -1152,
		"type": "TREE_1"
	},
	{
		"class": "io.github.pokemeetup.system.gameplay.overworld.World$WorldObjectData",
		"x": -8736,
		"y": -1376,
		"type": "TREE_1"
	},
	{
		"class": "io.github.pokemeetup.system.gameplay.overworld.World$WorldObjectData",
		"x": -9152,
		"y": -1440,
		"type": "POKEBALL"
	}
],
"blocks": [],
"lastModified": 0,
"isMultiplayer": false
}