{
"x": -83,
"y": -15,
"biomeType": "SNOW",
"tileData": [
	[ 4, 4, 4, 4, 4, 4, 4, 4, 4, 4, 4, 6, 4, 4, 4, 4 ],
	[ 4, 4, 51, 4, 4, 6, 4, 4, 4, 51, 4, 4, 51, 4, 4, 4 ],
	[ 51, 6, 51, 4, 6, 4, 4, 6, 4, 4, 4, 51, 4, 4, 4, 4 ],
	[ 4, 4, 4, 52, 4, 4, 4, 6, 4, 4, 52, 4, 4, 4, 51, 4 ],
	[ 51, 4, 6, 4, 4, 4, 51, 4, 4, 4, 4, 4, 4, 6, 4, 4 ],
	[ 4, 6, 4, 52, 4, 4, 51, 4, 6, 4, 4, 4, 4, 4, 4, 4 ],
	[ 6, 4, 4, 4, 6, 6, 4, 6, 4, 4, 4, 4, 4, 4, 6, 4 ],
	[ 4, 4, 4, 4, 6, 6, 51, 4, 4, 51, 4, 51, 6, 6, 4, 6 ],
	[ 4, 4, 6, 4, 4, 6, 4, 4, 4, 51, 4, 6, 51, 6, 51, 4 ],
	[ 4, 4, 51, 4, 6, 4, 4, 4, 4, 6, 6, 6, 4, 4, 4, 4 ],
	[ 51, 4, 52, 4, 4, 4, 4, 6, 4, 4, 6, 4, 4, 4, 4, 4 ],
	[ 4, 4, 4, 4, 4, 4, 51, 4, 4, 51, 4, 4, 51, 6, 4, 4 ],
	[ 52, 6, 4, 4, 4, 4, 4, 6, 4, 4, 6, 6, 6, 4, 6, 4 ],
	[ 4, 4, 4, 4, 4, 51, 4, 6, 4, 4, 4, 4, 51, 4, 4, 4 ],
	[ 4, 4, 4, 4, 4, 6, 4, 4, 6, 51, 4, 51, 4, 4, 4, 4 ],
	[ 4, 4, 4, 6, 4, 4, 4, 4, 4, 51, 51, 4, 4, 4, 4, 4 ]
],
"objects": [
	{
		"class": "io.github.pokemeetup.system.gameplay.overworld.World$WorldObjectData",
		"x": -42080,
		"y": -7328,
		"type": "SNOW_TREE"
	},
	{
		"class": "io.github.pokemeetup.system.gameplay.overworld.World$WorldObjectData",
		"x": -42272,
		"y": -7296,
		"type": "SNOW_TREE"
	},
	{
		"class": "io.github.pokemeetup.system.gameplay.overworld.World$WorldObjectData",
		"x": -42208,
		"y": -7552,
		"type": "SNOW_TREE"
	},
	{
		"class": "io.github.pokemeetup.system.gameplay.overworld.World$WorldObjectData",
		"x": -42112,
		"y": -7648,
		"type": "SNOW_TREE"
	},
	{
		"class": "io.github.pokemeetup.system.gameplay.overworld.World$WorldObjectData",
		"x": -42496,
		"y": -7328,
		"type": "SNOW_TREE"
	},
	{
		"class": "io.github.pokemeetup.system.gameplay.overworld.World$WorldObjectData",
		"x": -42400,
		"y": -7424,
		"type": "SNOW_TREE"
	},
	{
		"class": "io.github.pokemeetup.system.gameplay.overworld.World$WorldObjectData",
		"x": -42048,
		"y": -7424,
		"type": "SNOW_TREE"
	},
	{
		"class": "io.github.pokemeetup.system.gameplay.overworld.World$WorldObjectData",
		"x": -42432,
		"y": -7648,
		"type": "SNOW_TREE"
	},
	{
		"class": "io.github.pokemeetup.system.gameplay.overworld.World$WorldObjectData",
		"x": -42080,
		"y": -7200,
		"type": "SNOW_TREE"
	},
	{
		"class": "io.github.pokemeetup.system.gameplay.overworld.World$WorldObjectData",
		"x": -42400,
		"y": -7520,
		"type": "SNOW_TREE"
	},
	{
		"class": "io.github.pokemeetup.system.gameplay.overworld.World$WorldObjectData",
		"x": -42208,
		"y": -7424,
		"type": "SNOW_TREE"
	},
	{
		"class": "io.github.pokemeetup.system.gameplay.overworld.World$WorldObjectData",
		"x": -42336,
		"y": -7680,
		"type": "SNOW_TREE"
	},
	{
		"class": "io.github.pokemeetup.system.gameplay.overworld.World$WorldObjectData",
		"x": -42304,
		"y": -7200,
		"type": "SNOW_TREE"
	},
	{
		"class": "io.github.pokemeetup.system.gameplay.overworld.World$WorldObjectData",
		"x": -42496,
		"y": -7552,
		"type": "SNOW_TREE"
	},
	{
		"class": "io.github.pokemeetup.system.gameplay.overworld.World$WorldObjectData",
		"x": -42240,
		"y": -7648,
		"type": "SNOW_TREE"
	}
],
"blocks": [],
"lastModified": 0,
"isMultiplayer": false
}