{
"x": -13,
"y": -4,
"biomeType": "HAUNTED",
"tileData": [
	[ 5, 5, 8, 7, 8, 7, 5, 5, 5, 7, 5, 5, 7, 1, 5, 5 ],
	[ 5, 8, 7, 7, 5, 7, 5, 5, 7, 5, 9, 8, 7, 5, 5, 5 ],
	[ 7, 7, 7, 1, 1, 5, 5, 7, 7, 5, 7, 1, 5, 5, 7, 8 ],
	[ 5, 7, 1, 5, 5, 5, 5, 7, 5, 5, 7, 5, 5, 5, 7, 5 ],
	[ 5, 7, 10, 9, 7, 5, 5, 5, 9, 5, 5, 5, 5, 8, 5, 5 ],
	[ 10, 7, 5, 5, 5, 7, 5, 5, 5, 5, 5, 1, 7, 9, 7, 5 ],
	[ 5, 5, 5, 7, 8, 7, 5, 5, 5, 5, 10, 7, 5, 5, 5, 5 ],
	[ 5, 5, 5, 7, 5, 8, 9, 5, 5, 5, 5, 7, 7, 5, 5, 5 ],
	[ 7, 7, 5, 5, 7, 9, 5, 5, 10, 5, 5, 8, 5, 5, 5, 5 ],
	[ 10, 9, 7, 7, 5, 5, 5, 7, 10, 5, 9, 10, 5, 5, 5, 1 ],
	[ 5, 8, 7, 9, 7, 5, 7, 8, 5, 5, 9, 5, 5, 7, 7, 5 ],
	[ 5, 7, 5, 5, 5, 5, 7, 5, 5, 1, 8, 5, 5, 5, 5, 8 ],
	[ 7, 5, 5, 5, 5, 5, 5, 5, 5, 9, 5, 5, 7, 5, 5, 5 ],
	[ 7, 5, 5, 5, 5, 5, 7, 5, 5, 5, 1, 5, 5, 8, 5, 5 ],
	[ 5, 5, 5, 5, 9, 5, 5, 5, 5, 7, 5, 8, 7, 5, 5, 5 ],
	[ 5, 5, 5, 5, 7, 7, 5, 5, 5, 9, 5, 7, 9, 5, 7, 5 ]
],
"objects": [
	{
		"class": "io.github.pokemeetup.system.gameplay.overworld.World$WorldObjectData",
		"x": -6240,
		"y": -1696,
		"type": "HAUNTED_TREE"
	},
	{
		"class": "io.github.pokemeetup.system.gameplay.overworld.World$WorldObjectData",
		"x": -6432,
		"y": -1664,
		"type": "HAUNTED_TREE"
	},
	{
		"class": "io.github.pokemeetup.system.gameplay.overworld.World$WorldObjectData",
		"x": -6368,
		"y": -1920,
		"type": "HAUNTED_TREE"
	},
	{
		"class": "io.github.pokemeetup.system.gameplay.overworld.World$WorldObjectData",
		"x": -6272,
		"y": -2016,
		"type": "HAUNTED_TREE"
	},
	{
		"class": "io.github.pokemeetup.system.gameplay.overworld.World$WorldObjectData",
		"x": -6656,
		"y": -1696,
		"type": "HAUNTED_TREE"
	},
	{
		"class": "io.github.pokemeetup.system.gameplay.overworld.World$WorldObjectData",
		"x": -6560,
		"y": -1792,
		"type": "HAUNTED_TREE"
	},
	{
		"class": "io.github.pokemeetup.system.gameplay.overworld.World$WorldObjectData",
		"x": -6208,
		"y": -1792,
		"type": "HAUNTED_TREE"
	},
	{
		"class": "io.github.pokemeetup.system.gameplay.overworld.World$WorldObjectData",
		"x": -6592,
		"y": -2016,
		"type": "HAUNTED_TREE"
	},
	{
		"class": "io.github.pokemeetup.system.gameplay.overworld.World$WorldObjectData",
		"x": -6240,
		"y": -1568,
		"type": "HAUNTED_TREE"
	},
	{
		"class": "io.github.pokemeetup.system.gameplay.overworld.World$WorldObjectData",
		"x": -6560,
		"y": -1888,
		"type": "HAUNTED_TREE"
	},
	{
		"class": "io.github.pokemeetup.system.gameplay.overworld.World$WorldObjectData",
		"x": -6464,
		"y": -1568,
		"type": "HAUNTED_TREE"
	},
	{
		"class": "io.github.pokemeetup.system.gameplay.overworld.World$WorldObjectData",
		"x": -6656,
		"y": -1920,
		"type": "HAUNTED_TREE"
	},
	{
		"class": "io.github.pokemeetup.system.gameplay.overworld.World$WorldObjectData",
		"x": -6400,
		"y": -2016,
		"type": "HAUNTED_TREE"
	},
	{
		"class": "io.github.pokemeetup.system.gameplay.overworld.World$WorldObjectData",
		"x": -6336,
		"y": -1824,
		"type": "HAUNTED_TREE"
	},
	{
		"class": "io.github.pokemeetup.system.gameplay.overworld.World$WorldObjectData",
		"x": -6464,
		"y": -1856,
		"type": "HAUNTED_TREE"
	},
	{
		"class": "io.github.pokemeetup.system.gameplay.overworld.World$WorldObjectData",
		"x": -6656,
		"y": -1568,
		"type": "HAUNTED_TREE"
	},
	{
		"class": "io.github.pokemeetup.system.gameplay.overworld.World$WorldObjectData",
		"x": -6656,
		"y": -1792,
		"type": "HAUNTED_TREE"
	},
	{
		"class": "io.github.pokemeetup.system.gameplay.overworld.World$WorldObjectData",
		"x": -6272,
		"y": -1920,
		"type": "HAUNTED_TREE"
	},
	{
		"class": "io.github.pokemeetup.system.gameplay.overworld.World$WorldObjectData",
		"x": -6528,
		"y": -1664,
		"type": "HAUNTED_TREE"
	},
	{
		"class": "io.github.pokemeetup.system.gameplay.overworld.World$WorldObjectData",
		"x": -6176,
		"y": -1888,
		"type": "HAUNTED_TREE"
	},
	{
		"class": "io.github.pokemeetup.system.gameplay.overworld.World$WorldObjectData",
		"x": -6336,
		"y": -1696,
		"type": "HAUNTED_TREE"
	},
	{
		"class": "io.github.pokemeetup.system.gameplay.overworld.World$WorldObjectData",
		"x": -6432,
		"y": -1760,
		"type": "HAUNTED_TREE"
	},
	{
		"class": "io.github.pokemeetup.system.gameplay.overworld.World$WorldObjectData",
		"x": -6560,
		"y": -1568,
		"type": "HAUNTED_TREE"
	},
	{
		"class": "io.github.pokemeetup.system.gameplay.overworld.World$WorldObjectData",
		"x": -6496,
		"y": -2016,
		"type": "HAUNTED_TREE"
	},
	{
		"class": "io.github.pokemeetup.system.gameplay.overworld.World$WorldObjectData",
		"x": -6336,
		"y": -1568,
		"type": "HAUNTED_TREE"
	},
	{
		"class": "io.github.pokemeetup.system.gameplay.overworld.World$WorldObjectData",
		"x": -6176,
		"y": -1600,
		"type": "DEAD_TREE"
	},
	{
		"class": "io.github.pokemeetup.system.gameplay.overworld.World$WorldObjectData",
		"x": -6176,
		"y": -2048,
		"type": "DEAD_TREE"
	},
	{
		"class": "io.github.pokemeetup.system.gameplay.overworld.World$WorldObjectData",
		"x": -6592,
		"y": -1696,
		"type": "POKEBALL"
	}
],
"blocks": [],
"lastModified": 0,
"isMultiplayer": false
}